odoo/addons/shopinvader_delivery_carrier_category_keep_carrier/README.rst
odoo/addons/shopinvader_delivery_carrier_category_keep_carrier/__init__.py
odoo/addons/shopinvader_delivery_carrier_category_keep_carrier/__manifest__.py
odoo/addons/shopinvader_delivery_carrier_category_keep_carrier/i18n/shopinvader_delivery_carrier_category_keep_carrier.pot
odoo/addons/shopinvader_delivery_carrier_category_keep_carrier/models/__init__.py
odoo/addons/shopinvader_delivery_carrier_category_keep_carrier/models/delivery_carrier_category.py
odoo/addons/shopinvader_delivery_carrier_category_keep_carrier/readme/CONTRIBUTORS.rst
odoo/addons/shopinvader_delivery_carrier_category_keep_carrier/readme/DESCRIPTION.rst
odoo/addons/shopinvader_delivery_carrier_category_keep_carrier/readme/INSTALL.rst
odoo/addons/shopinvader_delivery_carrier_category_keep_carrier/readme/USAGE.rst
odoo/addons/shopinvader_delivery_carrier_category_keep_carrier/services/__init__.py
odoo/addons/shopinvader_delivery_carrier_category_keep_carrier/services/cart.py
odoo/addons/shopinvader_delivery_carrier_category_keep_carrier/static/description/icon.png
odoo/addons/shopinvader_delivery_carrier_category_keep_carrier/static/description/index.html
odoo/addons/shopinvader_delivery_carrier_category_keep_carrier/tests/__init__.py
odoo/addons/shopinvader_delivery_carrier_category_keep_carrier/tests/test_carrier.py
odoo/addons/shopinvader_delivery_carrier_category_keep_carrier/views/delivery_carrier_category.xml
odoo14_addon_shopinvader_delivery_carrier_category_keep_carrier-14.0.1.0.1.dist-info/METADATA
odoo14_addon_shopinvader_delivery_carrier_category_keep_carrier-14.0.1.0.1.dist-info/WHEEL
odoo14_addon_shopinvader_delivery_carrier_category_keep_carrier-14.0.1.0.1.dist-info/top_level.txt
odoo14_addon_shopinvader_delivery_carrier_category_keep_carrier-14.0.1.0.1.dist-info/RECORD
