Metadata-Version: 2.1
Name: odoo14-addon-shopinvader-delivery-carrier-category-keep-carrier
Version: 14.0.1.0.1
Summary: Allows to keep carrier even on delivery address change
Home-page: https://github.com/shopinvader/odoo-shopinvader
Author: ACSONE SA/NV,Odoo Community Association (OCA)
Author-email: support@odoo-community.org
License: AGPL-3
Platform: UNKNOWN
Classifier: Programming Language :: Python
Classifier: Framework :: Odoo
Classifier: Framework :: Odoo :: 14.0
Classifier: License :: OSI Approved :: GNU Affero General Public License v3
Requires-Python: >=3.6
Requires-Dist: odoo14-addon-delivery-carrier-category
Requires-Dist: odoo14-addon-shopinvader-delivery-carrier
Requires-Dist: odoo (<14.1dev,>=14.0a)
